stringtime/__init__.py
stringtime/__main__.py
stringtime/date.py
stringtime/parsetab.py
stringtime-0.0.6.dist-info/LICENSE.txt
stringtime-0.0.6.dist-info/METADATA
stringtime-0.0.6.dist-info/WHEEL
stringtime-0.0.6.dist-info/entry_points.txt
stringtime-0.0.6.dist-info/top_level.txt
stringtime-0.0.6.dist-info/RECORD
