Metadata-Version: 2.1
Name: stringtime
Version: 0.0.6
Summary: Create dates from natural language expressions
Home-page: https://github.com/byteface/stringtime
Author: @byteface
Author-email: byteface@gmail.com
License: MIT
Download-URL: https://github.com/byteface/stringtime/archive/0.0.6.tar.gz
Keywords: date,natural language,time
Platform: UNKNOWN
Classifier: Programming Language :: Python :: 3
Classifier: Programming Language :: Python
Classifier: Programming Language :: Python :: 3.7
Classifier: Programming Language :: Python :: 3.8
Classifier: Programming Language :: Python :: 3.9
Classifier: Programming Language :: Python :: 3.10
Classifier: Development Status :: 4 - Beta
Classifier: Intended Audience :: Developers
Classifier: Intended Audience :: Other Audience
Classifier: License :: OSI Approved :: MIT License
Classifier: Operating System :: OS Independent
Classifier: Topic :: Software Development
Classifier: Topic :: Terminals
Classifier: Topic :: Utilities
Classifier: Topic :: Software Development :: Libraries :: Python Modules
Requires-Python: >=3.6
License-File: LICENSE.txt
Requires-Dist: python-dateutil (==2.8.2)
Requires-Dist: ply (==3.11)
